{
  "type": "minecraft:block",
  "pools": [
    {
      "rolls": 1,
      "bonus_rolls": 0,
      "entries": [
        {
          "type": "minecraft:item",
          "name": "tsa:pebbles",
          "functions": [
            {
              "function": "minecraft:set_count",
              "count": 2,
              "add": false,
              "conditions": [
                {
                  "condition": "minecraft:block_state_property",
                  "block": "tsa:pebbles",
                  "properties": {
                    "count": "2"
                  }
                }
              ]
            },
            {
              "function": "minecraft:set_count",
              "count": 3,
              "add": false,
              "conditions": [
                {
                  "condition": "minecraft:block_state_property",
                  "block": "tsa:pebbles",
                  "properties": {
                    "count": "3"
                  }
                }
              ]
            },
            {
              "function": "minecraft:set_count",
              "count": 4,
              "add": false,
              "conditions": [
                {
                  "condition": "minecraft:block_state_property",
                  "block": "tsa:pebbles",
                  "properties": {
                    "count": "4"
                  }
                }
              ]
            },
            {
              "function": "minecraft:explosion_decay"
            }
          ]
        }
      ]
    }
  ],
  "random_sequence": "minecraft:blocks/black_candle"
}
